CHANGES.txt
LICENSE.txt
MANIFEST.in
setup.cfg
setup.py
enlivepy/__init__.py
enlivepy/common.py
enlivepy/snippet.py
enlivepy/template.py
enlivepy/transformers.py
enlivepy/utils.py
enlivepy.egg-info/PKG-INFO
enlivepy.egg-info/SOURCES.txt
enlivepy.egg-info/dependency_links.txt
enlivepy.egg-info/requires.txt
enlivepy.egg-info/top_level.txt
enlivepy/django/__init__.py
enlivepy/django/loader.py
enlivepy/django/registry.py
enlivepy/test/__init__.py
enlivepy/test/test.py
enlivepy/test/test_snippet.py