Metadata-Version: 1.1
Name: enlivepy
Version: 0.1.4
Summary: Html Tranformation Library
Home-page: https://github.com/makkalot/enlivepy
Author: makkalot
Author-email: makkalot@gmail.com
License: UNKNOWN
Keywords: templating,html,transformation
Platform: UNKNOWN
Classifier: Development Status :: 3 - Alpha
Classifier: License :: OSI Approved :: MIT License
Classifier: Programming Language :: Python
